byase/__init__.py
byase/annotation.py
byase/component.py
byase/db.py
byase/inference.py
byase/message.py
byase/pe_utils.py
byase/plot.py
byase/result.py
byase/run.py
byase/stats.py
byase/task/__init__.py
byase/task/align.py
byase/task/inference.py
byase/task/plot.py
byase/task/result.py
byase/task/task.py
byase-1.0.2.dist-info/LICENSE
byase-1.0.2.dist-info/METADATA
byase-1.0.2.dist-info/WHEEL
byase-1.0.2.dist-info/entry_points.txt
byase-1.0.2.dist-info/top_level.txt
byase-1.0.2.dist-info/RECORD
