Metadata-Version: 2.1
Name: byase
Version: 1.0.2
Summary: A library that uses Bayesian inference to identify gene-level and isoform-level ASE
Home-page: https://github.com/ncjllld/byase
Author: Lili Dong
Author-email: ncjllld@hit.edu.cn
License: UNKNOWN
Platform: UNKNOWN
Classifier: Programming Language :: Python :: 3
Classifier: License :: OSI Approved :: GNU General Public License v3 (GPLv3)
Classifier: Operating System :: OS Independent
Requires-Python: >=3.6
